mdsshellcommand/__init__.py
mdsshellcommand/libcommandrun.py
mdsshellcommand/runexample.py
mds_mdsshellcommand-0.6.5.dist-info/METADATA
mds_mdsshellcommand-0.6.5.dist-info/WHEEL
mds_mdsshellcommand-0.6.5.dist-info/top_level.txt
mds_mdsshellcommand-0.6.5.dist-info/RECORD
